airflowkit/__init__.py
airflowkit/sensors/__init__.py
airflowkit/sensors/gcs_any_objects_existence_async_sensor.py
airflowkit/sensors/gcs_objects_existence_async_sensor.py
airflowkit/triggers/__init__.py
airflowkit/triggers/gcs_any_blobs_trigger.py
airflowkit/triggers/gcs_blobs_trigger.py
airflowkit-0.0.5.dist-info/LICENSE
airflowkit-0.0.5.dist-info/METADATA
airflowkit-0.0.5.dist-info/WHEEL
airflowkit-0.0.5.dist-info/top_level.txt
airflowkit-0.0.5.dist-info/RECORD
